cert_dossier-1.0.0.post1.dist-info/licenses/LICENSE
dossier/__init__.py
dossier/ccadb_client.py
dossier/cert_loader.py
dossier/crl_client.py
dossier/main.py
dossier/processor.py
dossier/report.py
dossier/revocation.py
dossier/statistics.py
cert_dossier-1.0.0.post1.dist-info/METADATA
cert_dossier-1.0.0.post1.dist-info/WHEEL
cert_dossier-1.0.0.post1.dist-info/entry_points.txt
cert_dossier-1.0.0.post1.dist-info/top_level.txt
cert_dossier-1.0.0.post1.dist-info/RECORD
