Metadata-Version: 2.4
Name: cert-dossier
Version: 1.0.0.post1
Summary: Generator for certificate reports conformant with CCADB IR Guidelines
Author-email: Corey Bonnell <corey.bonnell@digicert.com>, Michael Lettona <michael.lettona@digicert.com>, Alex Campbell <alex.campbell@digicert.com>
License: MIT
Project-URL: Homepage, https://github.com/digicert/dossier
Project-URL: Repository, https://github.com/digicert/dossier
Project-URL: Issues, https://github.com/digicert/dossier/issues
Keywords: certificates,x509,smime,ssl,tls,cryptography
Classifier: Development Status :: 5 - Production/Stable
Classifier: Intended Audience :: Information Technology
Classifier: Operating System :: OS Independent
Classifier: Programming Language :: Python :: 3.10
Classifier: Programming Language :: Python :: 3.11
Classifier: Programming Language :: Python :: 3.12
Classifier: Programming Language :: Python :: 3.13
Classifier: Programming Language :: Python :: 3.14
Classifier: Topic :: Security :: Cryptography
Requires-Python: >=3.10
License-File: LICENSE
Requires-Dist: cryptography>=42
Requires-Dist: tqdm
Requires-Dist: httpx
Requires-Dist: python-dateutil
Provides-Extra: dev
Requires-Dist: pytest; extra == "dev"
Requires-Dist: black; extra == "dev"
Dynamic: license-file
